{
  "CF103415058": {
    "contest_id": 1471,
    "language": "Java 8",
    "path": "codeforces/1471/C.java",
    "platform": "Codeforces",
    "problem_index": "C",
    "problem_name": "Strange Birthday Party",
    "problem_url": "https://codeforces.com/contest/1471/problem/C",
    "submission_id": "CF103415058",
    "submission_url": "https://codeforces.com/contest/1471/submission/103415058",
    "tags": [
      "brute force",
      "greedy",
      "sortings",
      "*1300"
    ],
    "timestamp": "Jan/05/2021 20:36"
  },
  "CF103448804": {
    "contest_id": 1471,
    "language": "Java 8",
    "path": "codeforces/1471/D.java",
    "platform": "Codeforces",
    "problem_index": "D",
    "problem_name": "Strange Definition",
    "problem_url": "https://codeforces.com/contest/1471/problem/D",
    "submission_id": "CF103448804",
    "submission_url": "https://codeforces.com/contest/1471/submission/103448804",
    "tags": [
      "bitmasks",
      "graphs",
      "hashing",
      "math",
      "number theory",
      "*1900"
    ],
    "timestamp": "Jan/05/2021 21:38"
  }
}